ftrack_constants/__init__.py
ftrack_constants/framework/__init__.py
ftrack_constants/framework/asset/__init__.py
ftrack_constants/framework/client/__init__.py
ftrack_constants/framework/component/__init__.py
ftrack_constants/framework/event/__init__.py
ftrack_constants/framework/plugin/__init__.py
ftrack_constants/framework/tools/__init__.py
ftrack_constants/framework/tools/types/__init__.py
ftrack_constants/qt/__init__.py
ftrack_constants/qt/theme/__init__.py
ftrack_constants/status/__init__.py
ftrack_constants-2.0.0.dist-info/LICENSE.txt
ftrack_constants-2.0.0.dist-info/METADATA
ftrack_constants-2.0.0.dist-info/WHEEL
ftrack_constants-2.0.0.dist-info/RECORD
