Metadata-Version: 2.1
Name: ftrack-constants
Version: 2.0.0
Summary: ftrack constants library
Home-page: https://ftrack.com
License: Apache-2.0
Author: ftrack Integrations Team
Author-email: integrations@backlight.co
Requires-Python: >=3.7,<3.12
Classifier: License :: OSI Approved :: Apache Software License
Classifier: Programming Language :: Python :: 3
Classifier: Programming Language :: Python :: 3.7
Classifier: Programming Language :: Python :: 3.8
Classifier: Programming Language :: Python :: 3.9
Classifier: Programming Language :: Python :: 3.10
Classifier: Programming Language :: Python :: 3.11
Provides-Extra: ftrack-libs
Requires-Dist: ftrack-utils (>=2.0.0,<3.0.0) ; extra == "ftrack-libs"
Project-URL: Repository, https://github.com/ftrackhq/integrations/tree/main/libs/constants
